{"data":{"user":{"name":"Sudeep Khandekar","bio":"I have experience in web development, machine learning and data analysis. I practice competitive programming in my free time. I am also 2000 rated on Lichess!","isHireable":false,"avatarUrl":"https://avatars.githubusercontent.com/u/83664116?u=6c03ef6df2c90c4f69db5d3217a634563c5c840a&v=4","location":"Mumbai, India","pinnedItems":{"totalCount":6,"edges":[{"node":{"name":"path-finding-gui","description":null,"forkCount":0,"stargazers":{"totalCount":0},"url":"https://github.com/sudeepkhandekar99/path-finding-gui","id":"MDEwOlJlcG9zaXRvcnkzNzEzNTA0NzI=","diskUsage":24703,"primaryLanguage":{"name":"HTML","color":"#e34c26"}}},{"node":{"name":"snake-ai","description":null,"forkCount":0,"stargazers":{"totalCount":0},"url":"https://github.com/sudeepkhandekar99/snake-ai","id":"MDEwOlJlcG9zaXRvcnkzNjY3NTQwMjU=","diskUsage":555,"primaryLanguage":{"name":"Python","color":"#3572A5"}}},{"node":{"name":"competitive-programming","description":null,"forkCount":0,"stargazers":{"totalCount":0},"url":"https://github.com/sudeepkhandekar99/competitive-programming","id":"MDEwOlJlcG9zaXRvcnkzNzM5MDQwNTk=","diskUsage":7,"primaryLanguage":{"name":"C++","color":"#f34b7d"}}},{"node":{"name":"sudoku-solver","description":null,"forkCount":0,"stargazers":{"totalCount":0},"url":"https://github.com/sudeepkhandekar99/sudoku-solver","id":"MDEwOlJlcG9zaXRvcnkzNzA2Mzc5NjQ=","diskUsage":4,"primaryLanguage":{"name":"Python","color":"#3572A5"}}},{"node":{"name":"opencv-lane-detection","description":null,"forkCount":0,"stargazers":{"totalCount":0},"url":"https://github.com/sudeepkhandekar99/opencv-lane-detection","id":"MDEwOlJlcG9zaXRvcnkzNjYwOTg4NDA=","diskUsage":38562,"primaryLanguage":{"name":"Python","color":"#3572A5"}}},{"node":{"name":"sudeepkhandekar99","description":null,"forkCount":0,"stargazers":{"totalCount":0},"url":"https://github.com/sudeepkhandekar99/sudeepkhandekar99","id":"MDEwOlJlcG9zaXRvcnkzNzIyMDA2ODI=","diskUsage":1730,"primaryLanguage":{"name":"JavaScript","color":"#f1e05a"}}}]}}}}